{
  "persona_id": "P024",
  "archetype_id": "skeptical_comparison_buyer",
  "archetype_name": "Skeptical Comparison Buyer",
  "variation_slot": "freelancer_solopreneur",
  "summary": "현금흐름과 작업 리듬을 같이 따지는 1인 사업자 검증형. 가격보다 배합 이유와 실제 전환 가치가 선명해야 움직이는 freelancer_solopreneur variation.",
  "cluster_tags": [
    "skeptical",
    "comparison_driven",
    "evidence_seeking",
    "freelancer_solopreneur"
  ],
  "profile": {
    "age_band": "30s-40s",
    "occupation": "freelancer_or_solopreneur",
    "life_context": "작업 시간 손실과 구매 비용이 바로 수익성에 닿는 1인 사업 환경",
    "digital_fluency": "medium_to_high"
  },
  "purchase_context": {
    "problem_awareness": "high",
    "urgency_level": "high",
    "budget_sensitivity": "medium_to_high",
    "current_alternative": "값이 저렴한 기본 제품을 쓰면서도 체감이 애매해 계속 비교 중",
    "buyer_role": "primary_decision_maker"
  },
  "decision_style": {
    "decision_speed": "deliberate",
    "trust_style": [
      "evidence",
      "benchmark",
      "specificity"
    ],
    "preferred_message_style": [
      "structured",
      "clear",
      "non_exaggerated"
    ],
    "disliked_message_style": [
      "marketing_speak",
      "empty_confidence",
      "fake_urgency"
    ]
  },
  "voice_preferences": {
    "preferred_voice_style": [
      "calm",
      "professional",
      "confident"
    ],
    "disliked_voice_style": [
      "too_excited",
      "too_casual",
      "performative"
    ],
    "length_tolerance": "medium"
  },
  "persuasion_triggers": [
    "ingredient_comparison",
    "clear_differentiation",
    "specific_body_example"
  ],
  "objection_profile": {
    "primary_type": "trust",
    "secondary_type": "inertia",
    "intensity": "high",
    "trigger_conditions": [
      "claims_lack_evidence",
      "value_over_current_budget_choice_is_unclear",
      "voice_sounds_overly_sales_driven"
    ],
    "resolution_requirements": [
      "comparison_table",
      "realistic_claims",
      "cost_and_routine_specific_example"
    ]
  },
  "likely_reaction_style": {
    "if_interested": "지금 쓰는 저가 제품과 배합 이유, 복용 편의 차이를 세세하게 비교한다",
    "if_unconvinced": "가격과 차별점이 애매하다고 보고 기존 저가 제품을 유지한다",
    "if_annoyed": "실제 근거 없이 프리미엄 분위기만 밀면 바로 제외한다"
  },
  "scoring_hints": {
    "engagement_boosts": [
      "comparison_framing",
      "evidence",
      "precise_language"
    ],
    "engagement_penalties": [
      "hype_language",
      "vague_superiority",
      "aggressive_urgency"
    ],
    "purchase_intent_boosts": [
      "clear_differentiation",
      "credible_evidence"
    ],
    "purchase_intent_penalties": [
      "lack_of_evidence",
      "me_too_positioning"
    ]
  }
}